Metadata-Version: 2.4
Name: vipro_python
Version: 3.68
Summary: A set of convenience functions to make writing python, mostly in jupyter notebooks, as efficient as possible.
Home-page: https://github.com/underpinning/vipro-python
Author: Tom Medhurst
Author-email: tom.medhurst@vigilantapps.com
License: MIT
Keywords: vipro jupyter jupyterlab notebook pika amqp convenience
License-File: LICENSE
Requires-Dist: cloud-sql-python-connector[pytds]
Requires-Dist: setuptools>=80.4.0
Requires-Dist: pytest
Requires-Dist: pika
Requires-Dist: twine==6.1.0
Requires-Dist: pandas==2.2.3
Requires-Dist: numpy
Requires-Dist: nameparser
Requires-Dist: jellyfish
Requires-Dist: google-cloud-storage
Requires-Dist: google-cloud-firestore
Requires-Dist: google-cloud-pubsub
Requires-Dist: google-cloud-secret-manager
Requires-Dist: cloudevents
Requires-Dist: tensorflow==2.19.0
Requires-Dist: requests==2.32.3
Requires-Dist: pylint==3.3.7
Requires-Dist: openpyxl==3.1.5
Requires-Dist: xlrd
Dynamic: author
Dynamic: author-email
Dynamic: description
Dynamic: home-page
Dynamic: keywords
Dynamic: license
Dynamic: license-file
Dynamic: requires-dist
Dynamic: summary
